colore/__init__.py
colore/__main__.py
colore/colors.py
colore/filter.py
colore/help.py
colore-1.0.0.dist-info/LICENSE
colore-1.0.0.dist-info/METADATA
colore-1.0.0.dist-info/WHEEL
colore-1.0.0.dist-info/entry_points.txt
colore-1.0.0.dist-info/top_level.txt
colore-1.0.0.dist-info/RECORD
