Metadata-Version: 2.1
Name: colore
Version: 1.0.0
Summary: CLI filter that looks for regular expressions in stdin and highlights matching lines using ANSI colors
Author-email: Allan Psicobyte <psicobyte@gmail.com>
License: GNU AFFERO GENERAL PUBLIC LICENSE
Project-URL: Homepage, https://bitbucket.org/psicobyte/colore
Project-URL: Documentation, https://bitbucket.org/psicobyte/colore/src/master/README.md
Project-URL: Repository, https://bitbucket.org/psicobyte/colore.git
Keywords: cli,color,filter,regex
Classifier: Environment :: Console
Classifier: License :: OSI Approved :: GNU Affero General Public License v3 or later (AGPLv3+)
Classifier: Operating System :: OS Independent
Classifier: Programming Language :: Python :: 3
Requires-Python: >=3.8
License-File: LICENSE
